bcom_client/__init__.py
bcom_client/auth.py
bcom_client/inventory.py
bcom_client/mock.py
bcom_client/py.typed
bcom_client/schema.py
bcom_client-0.1.0.dist-info/LICENSE.md
bcom_client-0.1.0.dist-info/METADATA
bcom_client-0.1.0.dist-info/WHEEL
bcom_client-0.1.0.dist-info/top_level.txt
bcom_client-0.1.0.dist-info/RECORD
