Metadata-Version: 2.1
Name: bcom-client
Version: 0.1.0
Summary: A python httpx client library for bananas-commerce
Home-page: https://github.com/5m/bananas-commerce/
Author: 5monkeys
Author-email: info@5monkeys.se
Project-URL: GitHub, https://github.com/5m/bananas-commerce/
Project-URL: Issues, https://github.com/5m/bananas-commerce/issues/
Keywords: bcom,,bcom-commerce,,bcom-client,,bcom_client,,bananas-commerce
Classifier: Development Status :: 3 - Alpha
Classifier: Intended Audience :: Developers
Classifier: License :: OSI Approved :: BSD License
Classifier: Operating System :: OS Independent
Classifier: Programming Language :: Python :: 3
Classifier: Programming Language :: Python :: 3.10
Classifier: Typing :: Typed
Requires-Python: >=3.10
License-File: LICENSE.md
Requires-Dist: pydantic (>=1.8.2)
Requires-Dist: httpx
Requires-Dist: respx
Provides-Extra: test
Requires-Dist: nox ; extra == 'test'
Requires-Dist: mypy (>=0.941) ; extra == 'test'
Requires-Dist: pytest ; extra == 'test'
